data_ingestion.py
main.py
autogpt/__init__.py
autogpt/__main__.py
autogpt/app.py
autogpt/chat.py
autogpt/cli.py
autogpt/configurator.py
autogpt/llm_utils.py
autogpt/logs.py
autogpt/plugins.py
autogpt/setup.py
autogpt/spinner.py
autogpt/token_counter.py
autogpt/utils.py
autogpt/workspace.py
autogpt/agent/__init__.py
autogpt/agent/agent.py
autogpt/agent/agent_manager.py
autogpt/commands/__init__.py
autogpt/commands/analyze_code.py
autogpt/commands/audio_text.py
autogpt/commands/command.py
autogpt/commands/execute_code.py
autogpt/commands/file_operations.py
autogpt/commands/git_operations.py
autogpt/commands/google_search.py
autogpt/commands/image_gen.py
autogpt/commands/improve_code.py
autogpt/commands/times.py
autogpt/commands/twitter.py
autogpt/commands/web_playwright.py
autogpt/commands/web_requests.py
autogpt/commands/web_selenium.py
autogpt/commands/write_tests.py
autogpt/config/__init__.py
autogpt/config/ai_config.py
autogpt/config/config.py
autogpt/config/singleton.py
autogpt/json_utils/__init__.py
autogpt/json_utils/json_fix_general.py
autogpt/json_utils/json_fix_llm.py
autogpt/json_utils/utilities.py
autogpt/memory/__init__.py
autogpt/memory/base.py
autogpt/memory/local.py
autogpt/memory/milvus.py
autogpt/memory/no_memory.py
autogpt/memory/pinecone.py
autogpt/memory/redismem.py
autogpt/memory/weaviate.py
autogpt/models/base_open_ai_plugin.py
autogpt/permanent_memory/__init__.py
autogpt/permanent_memory/sqlite3_store.py
autogpt/processing/__init__.py
autogpt/processing/html.py
autogpt/processing/text.py
autogpt/prompts/__init__.py
autogpt/prompts/generator.py
autogpt/prompts/prompt.py
autogpt/speech/__init__.py
autogpt/speech/base.py
autogpt/speech/brian.py
autogpt/speech/eleven_labs.py
autogpt/speech/gtts.py
autogpt/speech/macos_tts.py
autogpt/speech/say.py
autogpt/types/openai.py
benchmark/__init__.py
benchmark/benchmark_entrepeneur_gpt_with_difficult_user.py
scripts/__init__.py
scripts/check_requirements.py
agpt-0.2.2.dist-info/METADATA
agpt-0.2.2.dist-info/WHEEL
agpt-0.2.2.dist-info/licenses/LICENSE
agpt-0.2.2.dist-info/RECORD
