Metadata-Version: 2.1
Name: agpt
Version: 0.2.2
Summary: An open-source attempt to make GPT-4 autonomous
Project-URL: Homepage, https://github.com/Significant-Gravitas/Auto-GPT
Project-URL: Bug Tracker, https://github.com/Significant-Gravitas/Auto-GPT
Author-email: Torantulino <support@agpt.co>
License-File: LICENSE
Classifier: License :: OSI Approved :: MIT License
Classifier: Operating System :: OS Independent
Classifier: Programming Language :: Python :: 3
Requires-Python: >=3.8
